wizwalker/__init__.py
wizwalker/__main__.py
wizwalker/client.py
wizwalker/client_handler.py
wizwalker/combat/__init__.py
wizwalker/combat/card.py
wizwalker/combat/handler.py
wizwalker/combat/member.py
wizwalker/constants.py
wizwalker/errors.py
wizwalker/extensions/scripting/__init__.py
wizwalker/extensions/scripting/deck_builder.py
wizwalker/extensions/scripting/utils.py
wizwalker/file_readers/__init__.py
wizwalker/file_readers/cache_handler.py
wizwalker/file_readers/nif.py
wizwalker/file_readers/wad.py
wizwalker/hotkey.py
wizwalker/memory/__init__.py
wizwalker/memory/handler.py
wizwalker/memory/hooks.py
wizwalker/memory/instance_finder.py
wizwalker/memory/memory_object.py
wizwalker/memory/memory_objects/__init__.py
wizwalker/memory/memory_objects/actor_body.py
wizwalker/memory/memory_objects/behavior_instance.py
wizwalker/memory/memory_objects/behavior_template.py
wizwalker/memory/memory_objects/cam_view.py
wizwalker/memory/memory_objects/camera_controller.py
wizwalker/memory/memory_objects/character_registry.py
wizwalker/memory/memory_objects/client_duel_manager.py
wizwalker/memory/memory_objects/client_object.py
wizwalker/memory/memory_objects/client_tag_list.py
wizwalker/memory/memory_objects/client_zone.py
wizwalker/memory/memory_objects/combat_action.py
wizwalker/memory/memory_objects/combat_participant.py
wizwalker/memory/memory_objects/combat_resolver.py
wizwalker/memory/memory_objects/conditionals.py
wizwalker/memory/memory_objects/core_object.py
wizwalker/memory/memory_objects/core_template.py
wizwalker/memory/memory_objects/duel.py
wizwalker/memory/memory_objects/enums.py
wizwalker/memory/memory_objects/equipment_behavior.py
wizwalker/memory/memory_objects/equipment_set.py
wizwalker/memory/memory_objects/equipped_item_info.py
wizwalker/memory/memory_objects/equipped_slot_info.py
wizwalker/memory/memory_objects/fish.py
wizwalker/memory/memory_objects/fish_template.py
wizwalker/memory/memory_objects/fishing_manager.py
wizwalker-1.9.0.dist-info/entry_points.txt
wizwalker-1.9.0.dist-info/LICENSE
wizwalker-1.9.0.dist-info/METADATA
wizwalker-1.9.0.dist-info/WHEEL
wizwalker-1.9.0.dist-info/RECORD
